sharedkernel/common.py
sharedkernel/data_format_converter.py
sharedkernel/date_converter.py
sharedkernel/diff_utils.py
sharedkernel/file_validation.py
sharedkernel/jwt_service.py
sharedkernel/multipart_upload.py
sharedkernel/regex_masking.py
sharedkernel/s3_uploader.py
sharedkernel/string_extentions.py
sharedkernel/database/__init__.py
sharedkernel/database/audit_model.py
sharedkernel/database/mongo_generic_audit_repository.py
sharedkernel/database/mongo_generic_repository.py
sharedkernel/database/pagination_response_dto.py
sharedkernel/enum/__init__.py
sharedkernel/enum/error_code.py
sharedkernel/enum/sort_order.py
sharedkernel/exception/__init__.py
sharedkernel/exception/exception.py
sharedkernel/exception/exception_handlers.py
sharedkernel/normalizer/__init__.py
sharedkernel/normalizer/number_normalizer.py
sharedkernel/normalizer/phone_number_normalizer.py
sharedkernel/normalizer/string_normalizer.py
sharedkernel/objects/__init__.py
sharedkernel/objects/base_document.py
sharedkernel/objects/json_string_model.py
sharedkernel/objects/jwt_model.py
sharedkernel/objects/result.py
sharedkernel/objects/user_info.py
sharedkernel-2.4.0.dist-info/METADATA
sharedkernel-2.4.0.dist-info/WHEEL
sharedkernel-2.4.0.dist-info/top_level.txt
sharedkernel-2.4.0.dist-info/RECORD
