Metadata-Version: 2.4
Name: sharedkernel
Version: 2.4.0
Summary: sharekernel is a shared package between all python projects
Author: Smilinno
Requires-Dist: numpy
Requires-Dist: requests
Requires-Dist: pymongo
Requires-Dist: fastapi
Requires-Dist: PyJWT
Requires-Dist: persian_tools
Requires-Dist: sentry-sdk
Requires-Dist: jdatetime
Requires-Dist: persiantools
Requires-Dist: boto3==1.35.90
Requires-Dist: python-docx
Requires-Dist: mammoth
Requires-Dist: markdown
Requires-Dist: beautifulsoup4
Requires-Dist: deepdiff
Dynamic: author
Dynamic: description
Dynamic: description-content-type
Dynamic: requires-dist
Dynamic: summary
